pydlinear/__init__.py
pydlinear/__init__.pyi
pydlinear/__main__.py
pydlinear/_pydlinear.pyi
pydlinear/_pydlinear.so
pydlinear/py.typed
pydlinear-0.0.1.dist-info/WHEEL
pydlinear-0.0.1.dist-info/METADATA
pydlinear-0.0.1.dist-info/entry_points.txt
pydlinear-0.0.1.dist-info/RECORD
