Metadata-Version: 2.1
Name: pydlinear
Author: Ernesto Casablanca
Author-email: casablancaernesto@gmail.com
Home-page: https://github.com/TendTo/dlinear
License: BSD 3-Clause License
Summary: delta-complete SMT solver for linear theories over the reals
Project-URL: Source, https://github.com/TendTo/dlinear
Project-URL: Tracker, https://github.com/TendTo/dlinear5/issues
Classifier: Development Status :: 1 - Planning
Classifier: Intended Audience :: Developers
Classifier: Intended Audience :: Science/Research
Classifier: License :: OSI Approved :: BSD License
Classifier: Operating System :: POSIX :: Linux
Classifier: Programming Language :: C++
Classifier: Programming Language :: Python :: 3
Classifier: Programming Language :: Python :: 3.6
Classifier: Programming Language :: Python :: 3.7
Classifier: Programming Language :: Python :: 3.8
Classifier: Topic :: Scientific/Engineering :: Mathematics
Classifier: Topic :: Software Development :: Libraries :: Python Modules
Version: 0.0.1
